eth_rec/__init__.py
eth_rec/eth_rec.py
eth_rec-0.1.2.5.dist-info/entry_points.txt
eth_rec-0.1.2.5.dist-info/WHEEL
eth_rec-0.1.2.5.dist-info/METADATA
eth_rec-0.1.2.5.dist-info/RECORD
