Metadata-Version: 2.1
Name: eth-rec
Version: 0.1.2.5
Summary: Download ETH-Livestream
Author: Your Name
Author-email: you@example.com
Requires-Python: >=3.9,<4.0
Classifier: Programming Language :: Python :: 3
Classifier: Programming Language :: Python :: 3.10
Classifier: Programming Language :: Python :: 3.9
